<?xml version="1.0" encoding="utf-8"?>
<!DOCTYPE hibernate-mapping PUBLIC "-//Hibernate/Hibernate Mapping DTD 3.0//EN"
"http://hibernate.sourceforge.net/hibernate-mapping-3.0.dtd">
<!-- 
    Mapping file autogenerated by MyEclipse Persistence Tools
-->
<hibernate-mapping>
    <class name="com.sail.cot.domain.CotQuestion" table="cot_question">
        <id name="id" type="java.lang.Integer">
            <column name="ID" />
            <generator class="identity" />
        </id>
        <property name="queryPerson" type="java.lang.Integer">
            <column name="queryPerson"/>
        </property>
        <property name="queryTime" type="java.sql.Timestamp">
            <column name="queryTime" length="10" />
        </property>
        <property name="queryText" type="java.lang.String">
            <column name="queryText" length="2000" />
        </property>
        <property name="orderId" type="java.lang.Integer">
            <column name="orderId"/>
        </property>
        <property name="flag" type="java.lang.Integer">
            <column name="flag" />
        </property>
    </class>
</hibernate-mapping>
